{
  "id": "saul-tarvitz",
  "name": "Saul Tarvitz",
  "titles": "Saul Tarvitz Captain of the 10 th Company",
  "lore": "Saul Tarvitz was a company captain within the Emperor’s Children, respected by those who followed him and with a number of victories to his name. Tarvitz, however, was content to be a line officer and serve his Legion and Emperor in the field, and lacked the relentless ambition required to elevate him to the higher echelons of his Legion that was present in many of his contemporaries. Upon discovering the scale and scope of the treachery that was about to unfold on Isstvan III, Tarvitz took it upon himself to act, flying down to the surface to warn the Loyalists trapped there of the impending slaughter and aid them in the battle.",
  "basePoints": 215,
  "battlefieldRole": "Command",
  "modelDefinitions": [
    {
      "name": "Saul Tarvitz",
      "modelType": "Infantry",
      "modelSubTypes": [
        "Unique",
        "Command"
      ],
      "baseSizeMM": 32,
      "countInBase": 1,
      "isAdditionalModelType": true,
      "characteristics": {
        "M": 7,
        "WS": 6,
        "BS": 5,
        "S": 4,
        "T": 4,
        "W": 3,
        "I": 5,
        "A": 4,
        "LD": 10,
        "CL": 9,
        "WP": 9,
        "IN": 9,
        "SAV": 2,
        "INV": 4
      },
      "isLeader": true
    }
  ],
  "minModels": 1,
  "maxModels": 1,
  "pointsPerAdditionalModel": 0,
  "defaultWargear": [
    "charnabal-broadsword",
    "nemesis-bolter",
    "bolt-pistol",
    "frag-grenades",
    "krak-grenades"
  ],
  "wargearOptions": [],
  "specialRules": [
    {
      "name": "Hatred",
      "value": "Traitor"
    },
    {
      "name": "Officer of the Line",
      "value": "2"
    },
    {
      "name": "A Brother Betrayed"
    }
  ],
  "traits": [
    {
      "category": "Allegiance",
      "value": "Loyalist"
    },
    {
      "category": "Custom",
      "value": "Master of the Legion"
    },
    {
      "category": "Faction",
      "value": "Emperor's Children"
    }
  ],
  "unitType": "Infantry",
  "unitSubTypes": [
    "Unique",
    "Command"
  ],
  "dedicatedWeapons": [
    {
      "id": "saul-tarvitz-charnabal-broadsword",
      "name": "Charnabal broadsword",
      "category": "melee",
      "profile": {
        "initiativeModifier": "I",
        "attacksModifier": "A",
        "strengthModifier": {
          "op": "add",
          "value": 2
        },
        "ap": null,
        "damage": 1,
        "specialRules": [
          {
            "name": "Breaching",
            "value": "5+"
          },
          {
            "name": "Duellist’s Edge",
            "value": "1"
          }
        ],
        "traits": []
      }
    }
  ]
}
